pawnhub/__init__.py
pawnhub/display.py
pawnhub-0.3.0.dist-info/LICENSE
pawnhub-0.3.0.dist-info/METADATA
pawnhub-0.3.0.dist-info/WHEEL
pawnhub-0.3.0.dist-info/entry_points.txt
pawnhub-0.3.0.dist-info/top_level.txt
pawnhub-0.3.0.dist-info/RECORD
