Metadata-Version: 2.1
Name: pawnhub
Version: 0.3.0
Summary: CLI listing your online chess games results
Home-page: https://github.com/KraYmer/pawnhub
Author: Fabrice Laporte
Author-email: kraymer@gmail.com
License: MIT
Keywords: chess
Platform: ALL
Classifier: License :: OSI Approved :: MIT License
Classifier: Programming Language :: Python
Classifier: Environment :: Console
Classifier: Topic :: Games/Entertainment :: Board Games
Requires-Python: >=3.6
License-File: LICENSE
Requires-Dist: click
Requires-Dist: click-log
Requires-Dist: confuse
Requires-Dist: rich
Requires-Dist: pawnstore ==0.2.2
Provides-Extra: test
Requires-Dist: coverage >5 ; extra == 'test'
Requires-Dist: pytest >=6 ; extra == 'test'
